scut_ssvep_aperiod/__init__.py
scut_ssvep_aperiod/fooof_parameter/__init__.py
scut_ssvep_aperiod/fooof_parameter/decode_rebuild.py
scut_ssvep_aperiod/load_dataset/__init__.py
scut_ssvep_aperiod/load_dataset/dataset_Tsinghua_wearable.py
scut_ssvep_aperiod/load_dataset/dataset_base.py
scut_ssvep_aperiod/load_dataset/dataset_kalunga.py
scut_ssvep_aperiod/load_dataset/dataset_lee.py
scut_ssvep_aperiod/ssvep_aperiod/__init__.py
scut_ssvep_aperiod/ssvep_aperiod/ssvep_aperiod_Tsinghua.py
scut_ssvep_aperiod/ssvep_aperiod/ssvep_aperiod_average_lee.py
scut_ssvep_aperiod/ssvep_aperiod/ssvep_aperiod_kalunga.py
scut_ssvep_aperiod/ssvep_aperiod/ssvep_aperiod_lee.py
scut_ssvep_aperiod/ssvep_aperiod/ssvep_aperiod_lee_parameter.py
scut_ssvep_aperiod/ssvep_method/__init__.py
scut_ssvep_aperiod/ssvep_method/cca.py
scut_ssvep_aperiod/ssvep_method/fbcca.py
scut_ssvep_aperiod/ssvep_method/psda.py
scut_ssvep_aperiod/ssvep_method/ssvep_methd_base.py
scut_ssvep_aperiod/ssvep_method/tdca.py
scut_ssvep_aperiod/ssvep_method/trca.py
scut_ssvep_aperiod/utils/__init__.py
scut_ssvep_aperiod/utils/common_function.py
scut_ssvep_aperiod/utils/ttest_analysis.py
scut_ssvep_aperiod-0.0.1.dist-info/METADATA
scut_ssvep_aperiod-0.0.1.dist-info/WHEEL
scut_ssvep_aperiod-0.0.1.dist-info/top_level.txt
scut_ssvep_aperiod-0.0.1.dist-info/RECORD
