Metadata-Version: 2.1
Name: scut_ssvep_aperiod
Version: 0.0.1
Summary: aperiod extract and ssvep measure
Author: didi
Author-email: 3517725675@qq.com
Requires-Dist: numpy
Requires-Dist: fooof
Requires-Dist: mne
Requires-Dist: mne-icalabel
Requires-Dist: scikit-learn
Requires-Dist: scipy
Requires-Dist: statsmodels
